rs_distributions/__about__.py
rs_distributions/__init__.py
rs_distributions/distributions/__init__.py
rs_distributions/distributions/folded_normal.py
rs_distributions/distributions/rice.py
rs_distributions/modules/__init__.py
rs_distributions/modules/distribution.py
rs_distributions/modules/kl.py
rs_distributions/modules/transformed_parameter.py
rs_distributions/transforms/__init__.py
rs_distributions/transforms/fill_scale_tril.py
rs_distributions-0.0.3.dist-info/METADATA
rs_distributions-0.0.3.dist-info/WHEEL
rs_distributions-0.0.3.dist-info/licenses/LICENSE.txt
rs_distributions-0.0.3.dist-info/RECORD
