Metadata-Version: 2.3
Name: rs-distributions
Version: 0.0.3
Summary: Statistical distributions for structural biology
Project-URL: Documentation, https://github.com/rs-station/distributions#readme
Project-URL: Issues, https://github.com/rs-station/distributions/issues
Project-URL: Source, https://github.com/rs-station/distributions
Author-email: "Kevin M. Dalton" <kmdalton@fas.harvard.edu>, Minhuan Li <minhuanli@g.harvard.edu>, Luis Aldama <luis_aldama@g.harvard.edu>
License: MIT
Classifier: Development Status :: 4 - Beta
Classifier: Programming Language :: Python
Classifier: Programming Language :: Python :: 3.8
Classifier: Programming Language :: Python :: 3.9
Classifier: Programming Language :: Python :: 3.10
Classifier: Programming Language :: Python :: 3.11
Classifier: Programming Language :: Python :: 3.12
Classifier: Programming Language :: Python :: Implementation :: CPython
Classifier: Programming Language :: Python :: Implementation :: PyPy
Requires-Python: >=3.8
Requires-Dist: numpy<2.0.0; python_version < '3.10'
Requires-Dist: numpy>=2.1.1; python_version >= '3.10'
Requires-Dist: torch
